plone.app.portlets-6.0.3-py3.13-nspkg.pth
plone/app/portlets/TODO.rst
plone/app/portlets/__init__.py
plone/app/portlets/assignable.py
plone/app/portlets/cache.py
plone/app/portlets/checker.py
plone/app/portlets/configure.zcml
plone/app/portlets/interfaces.py
plone/app/portlets/manager.py
plone/app/portlets/meta.zcml
plone/app/portlets/metaconfigure.py
plone/app/portlets/metadirectives.py
plone/app/portlets/overrides.zcml
plone/app/portlets/permissions.zcml
plone/app/portlets/portletcontext.py
plone/app/portlets/storage.py
plone/app/portlets/testing.py
plone/app/portlets/utils.py
plone/app/portlets/browser/__init__.py
plone/app/portlets/browser/adding.py
plone/app/portlets/browser/configure.zcml
plone/app/portlets/browser/editmanager.py
plone/app/portlets/browser/formhelper.py
plone/app/portlets/browser/interfaces.py
plone/app/portlets/browser/manage.py
plone/app/portlets/browser/traversal.py
plone/app/portlets/browser/utils.py
plone/app/portlets/browser/viewlets.py
plone/app/portlets/browser/templates/column.pt
plone/app/portlets/browser/templates/dashboard-column.pt
plone/app/portlets/browser/templates/edit-manager-contextual.pt
plone/app/portlets/browser/templates/edit-manager-macros.pt
plone/app/portlets/browser/templates/edit-manager.pt
plone/app/portlets/browser/templates/error_message.pt
plone/app/portlets/browser/templates/footer.pt
plone/app/portlets/browser/templates/manage-content-type.pt
plone/app/portlets/browser/templates/manage-contextual.pt
plone/app/portlets/browser/templates/manage-dashboard.pt
plone/app/portlets/browser/templates/manage-group-dashboard.pt
plone/app/portlets/browser/templates/manage-group.pt
plone/app/portlets/browser/templates/manage_portlets_fallback.pt
plone/app/portlets/browser/templates/portlets-pageform.pt
plone/app/portlets/browser/templates/topbar-manage-portlets.pt
plone/app/portlets/browser/templates/z3cform-portlets-pageform.pt
plone/app/portlets/dashboard/__init__.py
plone/app/portlets/dashboard/configure.zcml
plone_app_portlets-6.0.3.dist-info/METADATA
plone_app_portlets-6.0.3.dist-info/WHEEL
plone_app_portlets-6.0.3.dist-info/namespace_packages.txt
plone_app_portlets-6.0.3.dist-info/top_level.txt
plone_app_portlets-6.0.3.dist-info/RECORD
