Metadata-Version: 2.4
Name: plone.app.portlets
Version: 6.0.3
Summary: Plone integration for the basic plone.portlets package
Home-page: https://github.com/plone/plone.app.portlets
Author: Plone Foundation
Author-email: plone-developers@lists.sourceforge.net
License: GPL version 2
Keywords: portlets viewlets plone
Classifier: Development Status :: 5 - Production/Stable
Classifier: Environment :: Web Environment
Classifier: Framework :: Plone
Classifier: Framework :: Plone :: 6.0
Classifier: Framework :: Plone :: Core
Classifier: Framework :: Zope :: 5
Classifier: License :: OSI Approved :: GNU General Public License v2 (GPLv2)
Classifier: Operating System :: OS Independent
Classifier: Programming Language :: Python
Classifier: Programming Language :: Python :: 3.8
Classifier: Programming Language :: Python :: 3.9
Classifier: Programming Language :: Python :: 3.10
Classifier: Programming Language :: Python :: 3.11
Requires-Python: >=3.8
Requires-Dist: setuptools
Requires-Dist: plone.base
Requires-Dist: Zope
Requires-Dist: BTrees
Requires-Dist: ExtensionClass
Requires-Dist: feedparser
Requires-Dist: five.customerize
Requires-Dist: plone.app.i18n
Requires-Dist: plone.app.layout
Requires-Dist: plone.app.uuid
Requires-Dist: plone.app.vocabularies
Requires-Dist: plone.app.z3cform
Requires-Dist: plone.autoform
Requires-Dist: plone.i18n
Requires-Dist: plone.memoize
Requires-Dist: plone.portlets
Requires-Dist: plone.protect
Requires-Dist: plone.registry
Requires-Dist: Products.GenericSetup
Requires-Dist: Products.MimetypesRegistry
Requires-Dist: Products.PluggableAuthService
Requires-Dist: Products.PythonScripts
Requires-Dist: Products.statusmessages
Requires-Dist: z3c.form
Requires-Dist: zope.annotation
Requires-Dist: zope.browser
Requires-Dist: zope.contentprovider
Provides-Extra: test
Requires-Dist: five.intid; extra == "test"
Requires-Dist: plone.app.testing; extra == "test"
Requires-Dist: plone.namedfile; extra == "test"
Requires-Dist: plone.testing; extra == "test"
Requires-Dist: plone.z3cform; extra == "test"
Requires-Dist: zope.intid; extra == "test"
Dynamic: author
Dynamic: author-email
Dynamic: classifier
Dynamic: description
Dynamic: home-page
Dynamic: keywords
Dynamic: license
Dynamic: provides-extra
Dynamic: requires-dist
Dynamic: requires-python
Dynamic: summary
